odoo/addons/web_widget_one2many_tree_line_duplicate/README.rst
odoo/addons/web_widget_one2many_tree_line_duplicate/__init__.py
odoo/addons/web_widget_one2many_tree_line_duplicate/__manifest__.py
odoo/addons/web_widget_one2many_tree_line_duplicate/i18n/it.po
odoo/addons/web_widget_one2many_tree_line_duplicate/i18n/web_widget_one2many_tree_line_duplicate.pot
odoo/addons/web_widget_one2many_tree_line_duplicate/readme/CONTRIBUTORS.rst
odoo/addons/web_widget_one2many_tree_line_duplicate/readme/DESCRIPTION.rst
odoo/addons/web_widget_one2many_tree_line_duplicate/readme/ROADMAP.rst
odoo/addons/web_widget_one2many_tree_line_duplicate/readme/USAGE.rst
odoo/addons/web_widget_one2many_tree_line_duplicate/static/description/icon.png
odoo/addons/web_widget_one2many_tree_line_duplicate/static/description/index.html
odoo/addons/web_widget_one2many_tree_line_duplicate/static/src/js/basic_model.js
odoo/addons/web_widget_one2many_tree_line_duplicate/static/src/js/one2many_tree_line_duplicate.js
odoo/addons/web_widget_one2many_tree_line_duplicate/static/src/scss/one2many_tree_line_duplicate.scss
odoo/addons/web_widget_one2many_tree_line_duplicate/view/assets.xml
odoo14_addon_web_widget_one2many_tree_line_duplicate-14.0.1.0.1.dev4.dist-info/METADATA
odoo14_addon_web_widget_one2many_tree_line_duplicate-14.0.1.0.1.dev4.dist-info/WHEEL
odoo14_addon_web_widget_one2many_tree_line_duplicate-14.0.1.0.1.dev4.dist-info/top_level.txt
odoo14_addon_web_widget_one2many_tree_line_duplicate-14.0.1.0.1.dev4.dist-info/RECORD
